sckan_compare/__init__.py
sckan_compare/globals.py
sckan_compare/query.py
sckan_compare/simplevis.py
sckan_compare/utils.py
sckan_compare/visualize.py
sckan_compare/data/coords_human.json
sckan_compare/data/coords_mouse.json
sckan_compare/data/coords_rat.json
sckan_compare/data/node_A.png
sckan_compare/data/node_B.png
sckan_compare/data/node_C.png
skcan_compare/__init__.py
skcan_compare/globals.py
skcan_compare/query.py
skcan_compare/visualize.py
skcan_compare/data/coords_human.json
sckan_compare-0.0.7.dist-info/LICENSE
sckan_compare-0.0.7.dist-info/METADATA
sckan_compare-0.0.7.dist-info/WHEEL
sckan_compare-0.0.7.dist-info/top_level.txt
sckan_compare-0.0.7.dist-info/RECORD
